password_vault/__init__.py
password_vault/vault.py
password_vault-1.0.0.dist-info/LICENSE
password_vault-1.0.0.dist-info/METADATA
password_vault-1.0.0.dist-info/WHEEL
password_vault-1.0.0.dist-info/RECORD
