Metadata-Version: 2.1
Name: password-vault
Version: 1.0.0
Summary: A simple python library to safely store your passwords using encription
License: Apache 2.0
Author: matteogabburo
Author-email: matteogabburo@gmail.com
Requires-Python: >=3.12,<4.0
Classifier: License :: Other/Proprietary License
Classifier: Programming Language :: Python :: 3
Classifier: Programming Language :: Python :: 3.12
Requires-Dist: cryptography (>=45.0.4,<46.0.0)
Requires-Dist: pynacl (>=1.5.0,<2.0.0)
